[{"title": "City/Town: Sharm ElSheikhNation:\u00a0EGYTournament type: ITF World Tennis TourSurface: Hard", "details": "Draw: Main DrawType: SinglesEntry: DA", "score": [{"surname": "Stewart", "first_name": "Hamish", "results": "R11st RoundLH2HvGBRHamishStewart", "score": "7-56-746-73"}, {"surname": "Safwat", "first_name": "Mohamed", "results": "QFQuarter-finalLH2HvEGYMohamedSafwat", "score": "6-32-65-7"}, {"surname": "Privara", "first_name": "Peter Benjamin", "results": "R22nd RoundWH2HvSVKPeter BenjaminPrivara", "score": "6-737-617-63"}, {"surname": "Nesterov", "first_name": "Petr", "results": "R11st RoundWH2HvBULPetrNesterov", "score": "6-32-66-2"}, {"surname": "Fajta", "first_name": "Peter", "results": "R11st RoundLH2HvHUNPeterFajta", "score": "1-64-6"}, {"surname": "Pokotilov", "first_name": "Boris", "results": "FFinalWH2HvBorisPokotilov", "score": "6-36-4"}, {"surname": "Rossi", "first_name": "Leonardo", "results": "SFSemi-finalWH2HvITALeonardoRossi", "score": "6-26-4"}, {"surname": "Fantini", "first_name": "Luca", "results": "QFQuarter-finalWH2HvITALucaFantini", "score": "6-16-4"}, {"surname": "Kielan", "first_name": "Szymon", "results": "R22nd RoundWH2HvPOLSzymonKielan", "score": "6-16-3"}, {"surname": "Zakaryia", "first_name": "Faris", "results": "R11st RoundWH2HvEGYFarisZakaryia", "score": "6-26-2"}, {"surname": "Veldheer", "first_name": "Mick", "results": "R22nd RoundLH2HvNEDMickVeldheer", "score": "4-66-75"}, {"surname": "Mikula", "first_name": "Michal", "results": "R11st RoundWH2HvPOLMichalMikula", "score": "6-26-4"}]}, {"title": "City/Town: Sharm ElSheikhNation:\u00a0EGYTournament type: ITF World Tennis TourSurface: Hard", "details": "Draw: Main DrawType: SinglesEntry: JR", "score": [{"surname": "Stewart", "first_name": "Hamish", "results": "R11st RoundLH2HvGBRHamishStewart", "score": "7-56-746-73"}, {"surname": "Safwat", "first_name": "Mohamed", "results": "QFQuarter-finalLH2HvEGYMohamedSafwat", "score": "6-32-65-7"}, {"surname": "Privara", "first_name": "Peter Benjamin", "results": "R22nd RoundWH2HvSVKPeter BenjaminPrivara", "score": "6-737-617-63"}, {"surname": "Nesterov", "first_name": "Petr", "results": "R11st RoundWH2HvBULPetrNesterov", "score": "6-32-66-2"}, {"surname": "Fajta", "first_name": "Peter", "results": "R11st RoundLH2HvHUNPeterFajta", "score": "1-64-6"}, {"surname": "Pokotilov", "first_name": "Boris", "results": "FFinalWH2HvBorisPokotilov", "score": "6-36-4"}, {"surname": "Rossi", "first_name": "Leonardo", "results": "SFSemi-finalWH2HvITALeonardoRossi", "score": "6-26-4"}, {"surname": "Fantini", "first_name": "Luca", "results": "QFQuarter-finalWH2HvITALucaFantini", "score": "6-16-4"}, {"surname": "Kielan", "first_name": "Szymon", "results": "R22nd RoundWH2HvPOLSzymonKielan", "score": "6-16-3"}, {"surname": "Zakaryia", "first_name": "Faris", "results": "R11st RoundWH2HvEGYFarisZakaryia", "score": "6-26-2"}, {"surname": "Veldheer", "first_name": "Mick", "results": "R22nd RoundLH2HvNEDMickVeldheer", "score": "4-66-75"}, {"surname": "Mikula", "first_name": "Michal", "results": "R11st RoundWH2HvPOLMichalMikula", "score": "6-26-4"}]}, {"title": "City/Town: Sharm ElSheikhNation:\u00a0EGYTournament type: ITF World Tennis TourSurface: Hard", "details": "Draw: Main DrawType: SinglesEntry: DA", "score": [{"surname": "Stewart", "first_name": "Hamish", "results": "R11st RoundLH2HvGBRHamishStewart", "score": "7-56-746-73"}, {"surname": "Safwat", "first_name": "Mohamed", "results": "QFQuarter-finalLH2HvEGYMohamedSafwat", "score": "6-32-65-7"}, {"surname": "Privara", "first_name": "Peter Benjamin", "results": "R22nd RoundWH2HvSVKPeter BenjaminPrivara", "score": "6-737-617-63"}, {"surname": "Nesterov", "first_name": "Petr", "results": "R11st RoundWH2HvBULPetrNesterov", "score": "6-32-66-2"}, {"surname": "Fajta", "first_name": "Peter", "results": "R11st RoundLH2HvHUNPeterFajta", "score": "1-64-6"}, {"surname": "Pokotilov", "first_name": "Boris", "results": "FFinalWH2HvBorisPokotilov", "score": "6-36-4"}, {"surname": "Rossi", "first_name": "Leonardo", "results": "SFSemi-finalWH2HvITALeonardoRossi", "score": "6-26-4"}, {"surname": "Fantini", "first_name": "Luca", "results": "QFQuarter-finalWH2HvITALucaFantini", "score": "6-16-4"}, {"surname": "Kielan", "first_name": "Szymon", "results": "R22nd RoundWH2HvPOLSzymonKielan", "score": "6-16-3"}, {"surname": "Zakaryia", "first_name": "Faris", "results": "R11st RoundWH2HvEGYFarisZakaryia", "score": "6-26-2"}, {"surname": "Veldheer", "first_name": "Mick", "results": "R22nd RoundLH2HvNEDMickVeldheer", "score": "4-66-75"}, {"surname": "Mikula", "first_name": "Michal", "results": "R11st RoundWH2HvPOLMichalMikula", "score": "6-26-4"}]}, {"title": "City/Town: Sharm ElSheikhNation:\u00a0EGYTournament type: ITF World Tennis TourSurface: Hard", "details": "Draw: Main DrawType: SinglesEntry: JR", "score": [{"surname": "Stewart", "first_name": "Hamish", "results": "R11st RoundLH2HvGBRHamishStewart", "score": "7-56-746-73"}, {"surname": "Safwat", "first_name": "Mohamed", "results": "QFQuarter-finalLH2HvEGYMohamedSafwat", "score": "6-32-65-7"}, {"surname": "Privara", "first_name": "Peter Benjamin", "results": "R22nd RoundWH2HvSVKPeter BenjaminPrivara", "score": "6-737-617-63"}, {"surname": "Nesterov", "first_name": "Petr", "results": "R11st RoundWH2HvBULPetrNesterov", "score": "6-32-66-2"}, {"surname": "Fajta", "first_name": "Peter", "results": "R11st RoundLH2HvHUNPeterFajta", "score": "1-64-6"}, {"surname": "Pokotilov", "first_name": "Boris", "results": "FFinalWH2HvBorisPokotilov", "score": "6-36-4"}, {"surname": "Rossi", "first_name": "Leonardo", "results": "SFSemi-finalWH2HvITALeonardoRossi", "score": "6-26-4"}, {"surname": "Fantini", "first_name": "Luca", "results": "QFQuarter-finalWH2HvITALucaFantini", "score": "6-16-4"}, {"surname": "Kielan", "first_name": "Szymon", "results": "R22nd RoundWH2HvPOLSzymonKielan", "score": "6-16-3"}, {"surname": "Zakaryia", "first_name": "Faris", "results": "R11st RoundWH2HvEGYFarisZakaryia", "score": "6-26-2"}, {"surname": "Veldheer", "first_name": "Mick", "results": "R22nd RoundLH2HvNEDMickVeldheer", "score": "4-66-75"}, {"surname": "Mikula", "first_name": "Michal", "results": "R11st RoundWH2HvPOLMichalMikula", "score": "6-26-4"}]}, {"title": "City/Town: VilniusNation:\u00a0LTUTournament type: ITF World Tennis TourSurface: Hard", "details": "Draw: Main DrawType: SinglesEntry: DA", "score": [{"surname": "Stewart", "first_name": "Hamish", "results": "R11st RoundLH2HvGBRHamishStewart", "score": "7-56-746-73"}, {"surname": "Safwat", "first_name": "Mohamed", "results": "QFQuarter-finalLH2HvEGYMohamedSafwat", "score": "6-32-65-7"}, {"surname": "Privara", "first_name": "Peter Benjamin", "results": "R22nd RoundWH2HvSVKPeter BenjaminPrivara", "score": "6-737-617-63"}, {"surname": "Nesterov", "first_name": "Petr", "results": "R11st RoundWH2HvBULPetrNesterov", "score": "6-32-66-2"}, {"surname": "Fajta", "first_name": "Peter", "results": "R11st RoundLH2HvHUNPeterFajta", "score": "1-64-6"}, {"surname": "Pokotilov", "first_name": "Boris", "results": "FFinalWH2HvBorisPokotilov", "score": "6-36-4"}, {"surname": "Rossi", "first_name": "Leonardo", "results": "SFSemi-finalWH2HvITALeonardoRossi", "score": "6-26-4"}, {"surname": "Fantini", "first_name": "Luca", "results": "QFQuarter-finalWH2HvITALucaFantini", "score": "6-16-4"}, {"surname": "Kielan", "first_name": "Szymon", "results": "R22nd RoundWH2HvPOLSzymonKielan", "score": "6-16-3"}, {"surname": "Zakaryia", "first_name": "Faris", "results": "R11st RoundWH2HvEGYFarisZakaryia", "score": "6-26-2"}, {"surname": "Veldheer", "first_name": "Mick", "results": "R22nd RoundLH2HvNEDMickVeldheer", "score": "4-66-75"}, {"surname": "Mikula", "first_name": "Michal", "results": "R11st RoundWH2HvPOLMichalMikula", "score": "6-26-4"}]}]